[{"Key":"6wXa5B0Uv4pN859w-2dyx5aBX13JWPuMsc_g2tr1eN8","Token":{"ClientId":"tripgalleryauthcode","CreationTime":"2018-04-12T14:06:08.2891988+00:00","LifeTime":1296000,"AccessToken":{"Audience":"https://boongaloocompanysts/identity/resources","Issuer":"https://boongaloocompanysts/identity","CreationTime":"2018-04-12T14:06:08.2877209+00:00","Lifetime":600,"Type":"access_token","Client":{"Enabled":true,"ClientId":"tripgalleryauthcode","ClientSecrets":[{"Description":null,"Value":"ScLxbBxYuOAZTv/P/tISHoS0CH2Iv7edvl255Y2r0Os=","Expiration":null,"Type":"SharedSecret"}],"ClientName":"Trip Gallery (Authorization Code)","ClientUri":null,"LogoUri":null,"RequireConsent":false,"AllowRememberConsent":true,"Flow":0,"AllowClientCredentialsOnly":false,"RedirectUris":["app:/com.boongaloo.ios","https://localhost:44346/Home/StsCallBackForAuthCodeClient"],"PostLogoutRedirectUris":["app:/com.boongaloo.ios.logout"],"AllowAccessToAllScopes":true,"AllowedScopes":[],"IdentityTokenLifetime":300,"AccessTokenLifetime":600,"AuthorizationCodeLifetime":300,"AbsoluteRefreshTokenLifetime":1296000,"SlidingRefreshTokenLifetime":1296000,"RefreshTokenUsage":0,"UpdateAccessTokenClaimsOnRefresh":false,"RefreshTokenExpiration":1,"AccessTokenType":0,"EnableLocalLogin":true,"IdentityProviderRestrictions":[],"IncludeJwtId":false,"Claims":[],"AlwaysSendClientClaims":false,"PrefixClientClaims":true,"AllowAccessToAllCustomGrantTypes":false,"AllowedCustomGrantTypes":[],"AllowedCorsOrigins":[]},"Claims":[{"Issuer":"LOCAL AUTHORITY","OriginalIssuer":"LOCAL AUTHORITY","Properties":{},"Subject":null,"Type":"client_id","Value":"tripgalleryauthcode","ValueType":"http://www.w3.org/2001/XMLSchema#string"},{"Issuer":"LOCAL AUTHORITY","OriginalIssuer":"LOCAL AUTHORITY","Properties":{},"Subject":null,"Type":"scope","Value":"openid","ValueType":"http://www.w3.org/2001/XMLSchema#string"},{"Issuer":"LOCAL AUTHORITY","OriginalIssuer":"LOCAL AUTHORITY","Properties":{},"Subject":null,"Type":"scope","Value":"profile","ValueType":"http://www.w3.org/2001/XMLSchema#string"},{"Issuer":"LOCAL AUTHORITY","OriginalIssuer":"LOCAL AUTHORITY","Properties":{},"Subject":null,"Type":"scope","Value":"address","ValueType":"http://www.w3.org/2001/XMLSchema#string"},{"Issuer":"LOCAL AUTHORITY","OriginalIssuer":"LOCAL AUTHORITY","Properties":{},"Subject":null,"Type":"scope","Value":"boongaloomanagement","ValueType":"http://www.w3.org/2001/XMLSchema#string"},{"Issuer":"LOCAL AUTHORITY","OriginalIssuer":"LOCAL AUTHORITY","Properties":{},"Subject":null,"Type":"scope","Value":"offline_access","ValueType":"http://www.w3.org/2001/XMLSchema#string"},{"Issuer":"LOCAL AUTHORITY","OriginalIssuer":"LOCAL AUTHORITY","Properties":{},"Subject":null,"Type":"sub","Value":"abd57701-1aa0-460d-8bdb-9d418ac714a5","ValueType":"http://www.w3.org/2001/XMLSchema#string"},{"Issuer":"LOCAL AUTHORITY","OriginalIssuer":"LOCAL AUTHORITY","Properties":{},"Subject":null,"Type":"amr","Value":"external","ValueType":"http://www.w3.org/2001/XMLSchema#string"},{"Issuer":"LOCAL AUTHORITY","OriginalIssuer":"LOCAL AUTHORITY","Properties":{},"Subject":null,"Type":"auth_time","Value":"1523541961","ValueType":"http://www.w3.org/2001/XMLSchema#integer"},{"Issuer":"LOCAL AUTHORITY","OriginalIssuer":"LOCAL AUTHORITY","Properties":{},"Subject":null,"Type":"idp","Value":"Facebook","ValueType":"http://www.w3.org/2001/XMLSchema#string"},{"Issuer":"LOCAL AUTHORITY","OriginalIssuer":"LOCAL AUTHORITY","Properties":{},"Subject":null,"Type":"email","Value":"tommyjenkins947@yahoo.com","ValueType":"http://www.w3.org/2001/XMLSchema#string"},{"Issuer":"LOCAL AUTHORITY","OriginalIssuer":"LOCAL AUTHORITY","Properties":{},"Subject":null,"Type":"given_name","Value":"Tommy Jenkins","ValueType":"http://www.w3.org/2001/XMLSchema#string"},{"Issuer":"LOCAL AUTHORITY","OriginalIssuer":"LOCAL AUTHORITY","Properties":{},"Subject":null,"Type":"family_name","Value":"","ValueType":"http://www.w3.org/2001/XMLSchema#string"}],"Version":3,"SubjectId":"abd57701-1aa0-460d-8bdb-9d418ac714a5","ClientId":"tripgalleryauthcode","Scopes":["openid","profile","address","boongaloomanagement","offline_access"]},"Subject":{"Claims":[{"Issuer":"LOCAL AUTHORITY","OriginalIssuer":"LOCAL AUTHORITY","Properties":{},"Subject":{"AuthenticationType":"idsrv","IsAuthenticated":true,"Actor":null,"BootstrapContext":null,"Claims":[{"Issuer":"LOCAL AUTHORITY","OriginalIssuer":"LOCAL AUTHORITY","Properties":{},"Type":"name","Value":"Tommy Jenkins","ValueType":"http://www.w3.org/2001/XMLSchema#string"},{"Issuer":"LOCAL AUTHORITY","OriginalIssuer":"LOCAL AUTHORITY","Properties":{},"Type":"amr","Value":"external","ValueType":"http://www.w3.org/2001/XMLSchema#string"},{"Issuer":"LOCAL AUTHORITY","OriginalIssuer":"LOCAL AUTHORITY","Properties":{},"Type":"idp","Value":"Facebook","ValueType":"http://www.w3.org/2001/XMLSchema#string"},{"Issuer":"LOCAL AUTHORITY","OriginalIssuer":"LOCAL AUTHORITY","Properties":{},"Type":"auth_time","Value":"1523541961","ValueType":"http://www.w3.org/2001/XMLSchema#integer"},{"Issuer":"LOCAL AUTHORITY","OriginalIssuer":"LOCAL AUTHORITY","Properties":{},"Type":"email","Value":"tommyjenkins947@yahoo.com","ValueType":"http://www.w3.org/2001/XMLSchema#string"},{"Issuer":"LOCAL AUTHORITY","OriginalIssuer":"LOCAL AUTHORITY","Properties":{},"Type":"given_name","Value":"Tommy Jenkins","ValueType":"http://www.w3.org/2001/XMLSchema#string"},{"Issuer":"LOCAL AUTHORITY","OriginalIssuer":"LOCAL AUTHORITY","Properties":{},"Type":"family_name","Value":"","ValueType":"http://www.w3.org/2001/XMLSchema#string"}],"Label":null,"Name":"Tommy Jenkins","NameClaimType":"name","RoleClaimType":"role"},"Type":"sub","Value":"abd57701-1aa0-460d-8bdb-9d418ac714a5","ValueType":"http://www.w3.org/2001/XMLSchema#string"},{"Issuer":"LOCAL AUTHORITY","OriginalIssuer":"LOCAL AUTHORITY","Properties":{},"Subject":{"AuthenticationType":"idsrv","IsAuthenticated":true,"Actor":null,"BootstrapContext":null,"Claims":[{"Issuer":"LOCAL AUTHORITY","OriginalIssuer":"LOCAL AUTHORITY","Properties":{},"Type":"sub","Value":"abd57701-1aa0-460d-8bdb-9d418ac714a5","ValueType":"http://www.w3.org/2001/XMLSchema#string"},{"Issuer":"LOCAL AUTHORITY","OriginalIssuer":"LOCAL AUTHORITY","Properties":{},"Type":"amr","Value":"external","ValueType":"http://www.w3.org/2001/XMLSchema#string"},{"Issuer":"LOCAL AUTHORITY","OriginalIssuer":"LOCAL AUTHORITY","Properties":{},"Type":"idp","Value":"Facebook","ValueType":"http://www.w3.org/2001/XMLSchema#string"},{"Issuer":"LOCAL AUTHORITY","OriginalIssuer":"LOCAL AUTHORITY","Properties":{},"Type":"auth_time","Value":"1523541961","ValueType":"http://www.w3.org/2001/XMLSchema#integer"},{"Issuer":"LOCAL AUTHORITY","OriginalIssuer":"LOCAL AUTHORITY","Properties":{},"Type":"email","Value":"tommyjenkins947@yahoo.com","ValueType":"http://www.w3.org/2001/XMLSchema#string"},{"Issuer":"LOCAL AUTHORITY","OriginalIssuer":"LOCAL AUTHORITY","Properties":{},"Type":"given_name","Value":"Tommy Jenkins","ValueType":"http://www.w3.org/2001/XMLSchema#string"},{"Issuer":"LOCAL AUTHORITY","OriginalIssuer":"LOCAL AUTHORITY","Properties":{},"Type":"family_name","Value":"","ValueType":"http://www.w3.org/2001/XMLSchema#string"}],"Label":null,"Name":"Tommy Jenkins","NameClaimType":"name","RoleClaimType":"role"},"Type":"name","Value":"Tommy Jenkins","ValueType":"http://www.w3.org/2001/XMLSchema#string"},{"Issuer":"LOCAL AUTHORITY","OriginalIssuer":"LOCAL AUTHORITY","Properties":{},"Subject":{"AuthenticationType":"idsrv","IsAuthenticated":true,"Actor":null,"BootstrapContext":null,"Claims":[{"Issuer":"LOCAL AUTHORITY","OriginalIssuer":"LOCAL AUTHORITY","Properties":{},"Type":"sub","Value":"abd57701-1aa0-460d-8bdb-9d418ac714a5","ValueType":"http://www.w3.org/2001/XMLSchema#string"},{"Issuer":"LOCAL AUTHORITY","OriginalIssuer":"LOCAL AUTHORITY","Properties":{},"Type":"name","Value":"Tommy Jenkins","ValueType":"http://www.w3.org/2001/XMLSchema#string"},{"Issuer":"LOCAL AUTHORITY","OriginalIssuer":"LOCAL AUTHORITY","Properties":{},"Type":"idp","Value":"Facebook","ValueType":"http://www.w3.org/2001/XMLSchema#string"},{"Issuer":"LOCAL AUTHORITY","OriginalIssuer":"LOCAL AUTHORITY","Properties":{},"Type":"auth_time","Value":"1523541961","ValueType":"http://www.w3.org/2001/XMLSchema#integer"},{"Issuer":"LOCAL AUTHORITY","OriginalIssuer":"LOCAL AUTHORITY","Properties":{},"Type":"email","Value":"tommyjenkins947@yahoo.com","ValueType":"http://www.w3.org/2001/XMLSchema#string"},{"Issuer":"LOCAL AUTHORITY","OriginalIssuer":"LOCAL AUTHORITY","Properties":{},"Type":"given_name","Value":"Tommy Jenkins","ValueType":"http://www.w3.org/2001/XMLSchema#string"},{"Issuer":"LOCAL AUTHORITY","OriginalIssuer":"LOCAL AUTHORITY","Properties":{},"Type":"family_name","Value":"","ValueType":"http://www.w3.org/2001/XMLSchema#string"}],"Label":null,"Name":"Tommy Jenkins","NameClaimType":"name","RoleClaimType":"role"},"Type":"amr","Value":"external","ValueType":"http://www.w3.org/2001/XMLSchema#string"},{"Issuer":"LOCAL AUTHORITY","OriginalIssuer":"LOCAL AUTHORITY","Properties":{},"Subject":{"AuthenticationType":"idsrv","IsAuthenticated":true,"Actor":null,"BootstrapContext":null,"Claims":[{"Issuer":"LOCAL AUTHORITY","OriginalIssuer":"LOCAL AUTHORITY","Properties":{},"Type":"sub","Value":"abd57701-1aa0-460d-8bdb-9d418ac714a5","ValueType":"http://www.w3.org/2001/XMLSchema#string"},{"Issuer":"LOCAL AUTHORITY","OriginalIssuer":"LOCAL AUTHORITY","Properties":{},"Type":"name","Value":"Tommy Jenkins","ValueType":"http://www.w3.org/2001/XMLSchema#string"},{"Issuer":"LOCAL AUTHORITY","OriginalIssuer":"LOCAL AUTHORITY","Properties":{},"Type":"amr","Value":"external","ValueType":"http://www.w3.org/2001/XMLSchema#string"},{"Issuer":"LOCAL AUTHORITY","OriginalIssuer":"LOCAL AUTHORITY","Properties":{},"Type":"auth_time","Value":"1523541961","ValueType":"http://www.w3.org/2001/XMLSchema#integer"},{"Issuer":"LOCAL AUTHORITY","OriginalIssuer":"LOCAL AUTHORITY","Properties":{},"Type":"email","Value":"tommyjenkins947@yahoo.com","ValueType":"http://www.w3.org/2001/XMLSchema#string"},{"Issuer":"LOCAL AUTHORITY","OriginalIssuer":"LOCAL AUTHORITY","Properties":{},"Type":"given_name","Value":"Tommy Jenkins","ValueType":"http://www.w3.org/2001/XMLSchema#string"},{"Issuer":"LOCAL AUTHORITY","OriginalIssuer":"LOCAL AUTHORITY","Properties":{},"Type":"family_name","Value":"","ValueType":"http://www.w3.org/2001/XMLSchema#string"}],"Label":null,"Name":"Tommy Jenkins","NameClaimType":"name","RoleClaimType":"role"},"Type":"idp","Value":"Facebook","ValueType":"http://www.w3.org/2001/XMLSchema#string"},{"Issuer":"LOCAL AUTHORITY","OriginalIssuer":"LOCAL AUTHORITY","Properties":{},"Subject":{"AuthenticationType":"idsrv","IsAuthenticated":true,"Actor":null,"BootstrapContext":null,"Claims":[{"Issuer":"LOCAL AUTHORITY","OriginalIssuer":"LOCAL AUTHORITY","Properties":{},"Type":"sub","Value":"abd57701-1aa0-460d-8bdb-9d418ac714a5","ValueType":"http://www.w3.org/2001/XMLSchema#string"},{"Issuer":"LOCAL AUTHORITY","OriginalIssuer":"LOCAL AUTHORITY","Properties":{},"Type":"name","Value":"Tommy Jenkins","ValueType":"http://www.w3.org/2001/XMLSchema#string"},{"Issuer":"LOCAL AUTHORITY","OriginalIssuer":"LOCAL AUTHORITY","Properties":{},"Type":"amr","Value":"external","ValueType":"http://www.w3.org/2001/XMLSchema#string"},{"Issuer":"LOCAL AUTHORITY","OriginalIssuer":"LOCAL AUTHORITY","Properties":{},"Type":"idp","Value":"Facebook","ValueType":"http://www.w3.org/2001/XMLSchema#string"},{"Issuer":"LOCAL AUTHORITY","OriginalIssuer":"LOCAL AUTHORITY","Properties":{},"Type":"email","Value":"tommyjenkins947@yahoo.com","ValueType":"http://www.w3.org/2001/XMLSchema#string"},{"Issuer":"LOCAL AUTHORITY","OriginalIssuer":"LOCAL AUTHORITY","Properties":{},"Type":"given_name","Value":"Tommy Jenkins","ValueType":"http://www.w3.org/2001/XMLSchema#string"},{"Issuer":"LOCAL AUTHORITY","OriginalIssuer":"LOCAL AUTHORITY","Properties":{},"Type":"family_name","Value":"","ValueType":"http://www.w3.org/2001/XMLSchema#string"}],"Label":null,"Name":"Tommy Jenkins","NameClaimType":"name","RoleClaimType":"role"},"Type":"auth_time","Value":"1523541961","ValueType":"http://www.w3.org/2001/XMLSchema#integer"},{"Issuer":"LOCAL AUTHORITY","OriginalIssuer":"LOCAL AUTHORITY","Properties":{},"Subject":{"AuthenticationType":"idsrv","IsAuthenticated":true,"Actor":null,"BootstrapContext":null,"Claims":[{"Issuer":"LOCAL AUTHORITY","OriginalIssuer":"LOCAL AUTHORITY","Properties":{},"Type":"sub","Value":"abd57701-1aa0-460d-8bdb-9d418ac714a5","ValueType":"http://www.w3.org/2001/XMLSchema#string"},{"Issuer":"LOCAL AUTHORITY","OriginalIssuer":"LOCAL AUTHORITY","Properties":{},"Type":"name","Value":"Tommy Jenkins","ValueType":"http://www.w3.org/2001/XMLSchema#string"},{"Issuer":"LOCAL AUTHORITY","OriginalIssuer":"LOCAL AUTHORITY","Properties":{},"Type":"amr","Value":"external","ValueType":"http://www.w3.org/2001/XMLSchema#string"},{"Issuer":"LOCAL AUTHORITY","OriginalIssuer":"LOCAL AUTHORITY","Properties":{},"Type":"idp","Value":"Facebook","ValueType":"http://www.w3.org/2001/XMLSchema#string"},{"Issuer":"LOCAL AUTHORITY","OriginalIssuer":"LOCAL AUTHORITY","Properties":{},"Type":"auth_time","Value":"1523541961","ValueType":"http://www.w3.org/2001/XMLSchema#integer"},{"Issuer":"LOCAL AUTHORITY","OriginalIssuer":"LOCAL AUTHORITY","Properties":{},"Type":"given_name","Value":"Tommy Jenkins","ValueType":"http://www.w3.org/2001/XMLSchema#string"},{"Issuer":"LOCAL AUTHORITY","OriginalIssuer":"LOCAL AUTHORITY","Properties":{},"Type":"family_name","Value":"","ValueType":"http://www.w3.org/2001/XMLSchema#string"}],"Label":null,"Name":"Tommy Jenkins","NameClaimType":"name","RoleClaimType":"role"},"Type":"email","Value":"tommyjenkins947@yahoo.com","ValueType":"http://www.w3.org/2001/XMLSchema#string"},{"Issuer":"LOCAL AUTHORITY","OriginalIssuer":"LOCAL AUTHORITY","Properties":{},"Subject":{"AuthenticationType":"idsrv","IsAuthenticated":true,"Actor":null,"BootstrapContext":null,"Claims":[{"Issuer":"LOCAL AUTHORITY","OriginalIssuer":"LOCAL AUTHORITY","Properties":{},"Type":"sub","Value":"abd57701-1aa0-460d-8bdb-9d418ac714a5","ValueType":"http://www.w3.org/2001/XMLSchema#string"},{"Issuer":"LOCAL AUTHORITY","OriginalIssuer":"LOCAL AUTHORITY","Properties":{},"Type":"name","Value":"Tommy Jenkins","ValueType":"http://www.w3.org/2001/XMLSchema#string"},{"Issuer":"LOCAL AUTHORITY","OriginalIssuer":"LOCAL AUTHORITY","Properties":{},"Type":"amr","Value":"external","ValueType":"http://www.w3.org/2001/XMLSchema#string"},{"Issuer":"LOCAL AUTHORITY","OriginalIssuer":"LOCAL AUTHORITY","Properties":{},"Type":"idp","Value":"Facebook","ValueType":"http://www.w3.org/2001/XMLSchema#string"},{"Issuer":"LOCAL AUTHORITY","OriginalIssuer":"LOCAL AUTHORITY","Properties":{},"Type":"auth_time","Value":"1523541961","ValueType":"http://www.w3.org/2001/XMLSchema#integer"},{"Issuer":"LOCAL AUTHORITY","OriginalIssuer":"LOCAL AUTHORITY","Properties":{},"Type":"email","Value":"tommyjenkins947@yahoo.com","ValueType":"http://www.w3.org/2001/XMLSchema#string"},{"Issuer":"LOCAL AUTHORITY","OriginalIssuer":"LOCAL AUTHORITY","Properties":{},"Type":"family_name","Value":"","ValueType":"http://www.w3.org/2001/XMLSchema#string"}],"Label":null,"Name":"Tommy Jenkins","NameClaimType":"name","RoleClaimType":"role"},"Type":"given_name","Value":"Tommy Jenkins","ValueType":"http://www.w3.org/2001/XMLSchema#string"},{"Issuer":"LOCAL AUTHORITY","OriginalIssuer":"LOCAL AUTHORITY","Properties":{},"Subject":{"AuthenticationType":"idsrv","IsAuthenticated":true,"Actor":null,"BootstrapContext":null,"Claims":[{"Issuer":"LOCAL AUTHORITY","OriginalIssuer":"LOCAL AUTHORITY","Properties":{},"Type":"sub","Value":"abd57701-1aa0-460d-8bdb-9d418ac714a5","ValueType":"http://www.w3.org/2001/XMLSchema#string"},{"Issuer":"LOCAL AUTHORITY","OriginalIssuer":"LOCAL AUTHORITY","Properties":{},"Type":"name","Value":"Tommy Jenkins","ValueType":"http://www.w3.org/2001/XMLSchema#string"},{"Issuer":"LOCAL AUTHORITY","OriginalIssuer":"LOCAL AUTHORITY","Properties":{},"Type":"amr","Value":"external","ValueType":"http://www.w3.org/2001/XMLSchema#string"},{"Issuer":"LOCAL AUTHORITY","OriginalIssuer":"LOCAL AUTHORITY","Properties":{},"Type":"idp","Value":"Facebook","ValueType":"http://www.w3.org/2001/XMLSchema#string"},{"Issuer":"LOCAL AUTHORITY","OriginalIssuer":"LOCAL AUTHORITY","Properties":{},"Type":"auth_time","Value":"1523541961","ValueType":"http://www.w3.org/2001/XMLSchema#integer"},{"Issuer":"LOCAL AUTHORITY","OriginalIssuer":"LOCAL AUTHORITY","Properties":{},"Type":"email","Value":"tommyjenkins947@yahoo.com","ValueType":"http://www.w3.org/2001/XMLSchema#string"},{"Issuer":"LOCAL AUTHORITY","OriginalIssuer":"LOCAL AUTHORITY","Properties":{},"Type":"given_name","Value":"Tommy Jenkins","ValueType":"http://www.w3.org/2001/XMLSchema#string"}],"Label":null,"Name":"Tommy Jenkins","NameClaimType":"name","RoleClaimType":"role"},"Type":"family_name","Value":"","ValueType":"http://www.w3.org/2001/XMLSchema#string"}],"Identities":[{"AuthenticationType":"idsrv","IsAuthenticated":true,"Actor":null,"BootstrapContext":null,"Claims":[{"Issuer":"LOCAL AUTHORITY","OriginalIssuer":"LOCAL AUTHORITY","Properties":{},"Type":"sub","Value":"abd57701-1aa0-460d-8bdb-9d418ac714a5","ValueType":"http://www.w3.org/2001/XMLSchema#string"},{"Issuer":"LOCAL AUTHORITY","OriginalIssuer":"LOCAL AUTHORITY","Properties":{},"Type":"name","Value":"Tommy Jenkins","ValueType":"http://www.w3.org/2001/XMLSchema#string"},{"Issuer":"LOCAL AUTHORITY","OriginalIssuer":"LOCAL AUTHORITY","Properties":{},"Type":"amr","Value":"external","ValueType":"http://www.w3.org/2001/XMLSchema#string"},{"Issuer":"LOCAL AUTHORITY","OriginalIssuer":"LOCAL AUTHORITY","Properties":{},"Type":"idp","Value":"Facebook","ValueType":"http://www.w3.org/2001/XMLSchema#string"},{"Issuer":"LOCAL AUTHORITY","OriginalIssuer":"LOCAL AUTHORITY","Properties":{},"Type":"auth_time","Value":"1523541961","ValueType":"http://www.w3.org/2001/XMLSchema#integer"},{"Issuer":"LOCAL AUTHORITY","OriginalIssuer":"LOCAL AUTHORITY","Properties":{},"Type":"email","Value":"tommyjenkins947@yahoo.com","ValueType":"http://www.w3.org/2001/XMLSchema#string"},{"Issuer":"LOCAL AUTHORITY","OriginalIssuer":"LOCAL AUTHORITY","Properties":{},"Type":"given_name","Value":"Tommy Jenkins","ValueType":"http://www.w3.org/2001/XMLSchema#string"},{"Issuer":"LOCAL AUTHORITY","OriginalIssuer":"LOCAL AUTHORITY","Properties":{},"Type":"family_name","Value":"","ValueType":"http://www.w3.org/2001/XMLSchema#string"}],"Label":null,"Name":"Tommy Jenkins","NameClaimType":"name","RoleClaimType":"role"}],"Identity":{"AuthenticationType":"idsrv","IsAuthenticated":true,"Actor":null,"BootstrapContext":null,"Claims":[{"Issuer":"LOCAL AUTHORITY","OriginalIssuer":"LOCAL AUTHORITY","Properties":{},"Type":"sub","Value":"abd57701-1aa0-460d-8bdb-9d418ac714a5","ValueType":"http://www.w3.org/2001/XMLSchema#string"},{"Issuer":"LOCAL AUTHORITY","OriginalIssuer":"LOCAL AUTHORITY","Properties":{},"Type":"name","Value":"Tommy Jenkins","ValueType":"http://www.w3.org/2001/XMLSchema#string"},{"Issuer":"LOCAL AUTHORITY","OriginalIssuer":"LOCAL AUTHORITY","Properties":{},"Type":"amr","Value":"external","ValueType":"http://www.w3.org/2001/XMLSchema#string"},{"Issuer":"LOCAL AUTHORITY","OriginalIssuer":"LOCAL AUTHORITY","Properties":{},"Type":"idp","Value":"Facebook","ValueType":"http://www.w3.org/2001/XMLSchema#string"},{"Issuer":"LOCAL AUTHORITY","OriginalIssuer":"LOCAL AUTHORITY","Properties":{},"Type":"auth_time","Value":"1523541961","ValueType":"http://www.w3.org/2001/XMLSchema#integer"},{"Issuer":"LOCAL AUTHORITY","OriginalIssuer":"LOCAL AUTHORITY","Properties":{},"Type":"email","Value":"tommyjenkins947@yahoo.com","ValueType":"http://www.w3.org/2001/XMLSchema#string"},{"Issuer":"LOCAL AUTHORITY","OriginalIssuer":"LOCAL AUTHORITY","Properties":{},"Type":"given_name","Value":"Tommy Jenkins","ValueType":"http://www.w3.org/2001/XMLSchema#string"},{"Issuer":"LOCAL AUTHORITY","OriginalIssuer":"LOCAL AUTHORITY","Properties":{},"Type":"family_name","Value":"","ValueType":"http://www.w3.org/2001/XMLSchema#string"}],"Label":null,"Name":"Tommy Jenkins","NameClaimType":"name","RoleClaimType":"role"}},"Version":4,"SubjectId":"abd57701-1aa0-460d-8bdb-9d418ac714a5","Scopes":["openid","profile","address","boongaloomanagement","offline_access"]}}]